intbitset.cp313-win_amd64.pyd
intbitset_helper.py
intbitset_version.py
intbitset-4.0.0.dist-info/AUTHORS.rst
intbitset-4.0.0.dist-info/CHANGELOG.rst
intbitset-4.0.0.dist-info/LICENSE
intbitset-4.0.0.dist-info/METADATA
intbitset-4.0.0.dist-info/README.rst
intbitset-4.0.0.dist-info/WHEEL
intbitset-4.0.0.dist-info/top_level.txt
intbitset-4.0.0.dist-info/RECORD
