Metadata-Version: 2.1
Name: intbitset
Version: 4.0.0
Summary: C-based extension implementing fast integer bit sets.
Home-page: http://github.com/inveniosoftware-contrib/intbitset/
Author: Invenio collaboration, maintained by Philippe Ombredanne and AboutCode.org
Author-email: pombredanne@nexb.com
License: LGPL-3.0-or-later
Platform: any
Classifier: Environment :: Console
Classifier: Intended Audience :: Developers
Classifier: License :: OSI Approved :: GNU Lesser General Public License v3 or later (LGPLv3+)
Classifier: Operating System :: OS Independent
Classifier: Programming Language :: Cython
Classifier: Programming Language :: C
Classifier: Programming Language :: Python
Classifier: Topic :: Software Development :: Libraries :: Python Modules
Classifier: Programming Language :: Python :: 3
License-File: LICENSE
License-File: AUTHORS.rst
License-File: README.rst
License-File: CHANGELOG.rst
Provides-Extra: tests
Requires-Dist: pytest; extra == "tests"
Requires-Dist: pytest-xdist; extra == "tests"
